{
    "matches": [
        {
            "id": 737017,
            "streamUrl": "https:\/\/watchasports.90live.in\/2026\/02\/juventus-vs-lazio.html"
        },
        {
            "id": 737023,
            "streamUrl": "https:\/\/watchasports.90live.in\/2026\/02\/sassuolo-vs-inter-milan.html"
        },
        {
            "id": 748364,
            "streamUrl": "https:\/\/watchasports.90live.in\/2026\/02\/valencia-vs-real-madrid.html"
        },
        {
            "id": 762117,
            "streamUrl": "https:\/\/watchasports.90live.in\/2026\/02\/noroeste-vs-santos.html"
        },
        {
            "id": 748369,
            "streamUrl": "https:\/\/watchasports.90live.in\/2026\/02\/atletico-madrid-vs-real-betis.html"
        },
        {
            "id": 740848,
            "streamUrl": "https:\/\/watchasports.90live.in\/2026\/02\/chelsea-vs-leeds-united.html"
        },
        {
            "id": 740853,
            "streamUrl": "https:\/\/watchasports.90live.in\/2026\/02\/sunderland-vs-liverpool.html"
        },
        {
            "id": 401845421,
            "streamUrl": "https:\/\/watchasports.90live.in\/2026\/02\/arkadag-vs-al-nassr-fc.html"
        },
        {
            "id": 762467,
            "streamUrl": "https:\/\/watchasports.90live.in\/2026\/02\/bayern-munich-vs-rb-leipzig.html"
        },
        {
            "id": 762467,
            "streamUrl": "https:\/\/watchasports.90live.in\/2026\/02\/bayern-munich-vs-rb-leipzig.html"
        },
        {
            "id": 1512736,
            "streamUrl": "https:\/\/watchasports.90live.in\/2026\/02\/india-vs-namibia.html"
        },
        {
            "id": 740847,
            "streamUrl": "https:\/\/watchasports.90live.in\/2026\/02\/brentford-vs-arsenal.html"
        },
        {
            "id": 401859849,
            "streamUrl": "https:\/\/watchasports.90live.in\/2026\/02\/atletico-madrid-vs-fc-barcelona.html"
        },
        {
            "id": 401850911,
            "streamUrl": "https:\/\/watchasports.90live.in\/2026\/02\/aston-villa-vs-newcastle-united.html"
        },
        {
            "id": 401850952,
            "streamUrl": "https:\/\/watchasports.90live.in\/2026\/02\/liverpool-vs-brighton.html"
        },
        {
            "id": 737032,
            "streamUrl": "https:\/\/watchasports.90live.in\/2026\/02\/inter-milan-vs-juventus.html"
        },
        {
            "id": 746913,
            "streamUrl": "https:\/\/watchasports.90live.in\/2026\/02\/werder-bremen-vs-bayern-munich.html"
        },
        {
            "id": 748383,
            "streamUrl": "https:\/\/watchasports.90live.in\/2026\/02\/real-madrid-vs-real-sociedad.html"
        },
        {
            "id": 1512741,
            "streamUrl": "https:\/\/watchasports.90live.in\/2026\/02\/england-vs-scotland.html"
        },
        {
            "id": 1512742,
            "streamUrl": "https:\/\/watchasports.90live.in\/2026\/02\/new-zealand-vs-south-africa.html"
        },
        {
            "id": 1512741,
            "streamUrl": "https:\/\/watchasports.90live.in\/2026\/02\/england-vs-scotland.html"
        },
        {
            "id": 1512742,
            "streamUrl": "https:\/\/watchasports.90live.in\/2026\/02\/new-zealand-vs-south-africa.html"
        },
        {
            "id": 756100,
            "streamUrl": "https:\/\/watchasports.90live.in\/2026\/02\/al-fateh-vs-al-nassr.html"
        },
        {
            "id": 756100,
            "streamUrl": "https:\/\/watchasports.90live.in\/2026\/02\/al-fateh-vs-al-nassr.html"
        },
        {
            "id": 1512745,
            "streamUrl": "https:\/\/watchasports.90live.in\/2026\/02\/india-vs-pakistan.html"
        },
        {
            "id": 1512744,
            "streamUrl": "https:\/\/watchasports.90live.in\/2026\/02\/usa-vs-namibia.html"
        },
        {
            "id": 401859973,
            "streamUrl": "https:\/\/watchasports.90live.in\/2026\/02\/jamshedpur-vs-mohammedan-sc.html"
        },
        {
            "id": 401860523,
            "streamUrl": "https:\/\/watchasports.90live.in\/2026\/02\/bengaluru-fc-vs-sc-delhi.html"
        },
        {
            "id": 401850951,
            "streamUrl": "https:\/\/watchasports.90live.in\/2026\/02\/arsenal-vs-wigan.html"
        },
        {
            "id": 401840867,
            "streamUrl": "https:\/\/watchasports.90live.in\/2026\/02\/santos-vs-velo-clube.html"
        },
        {
            "id": 748382,
            "streamUrl": "https:\/\/watchasports.90live.in\/2026\/02\/rayo-vallecano-vs-atletico-madrid.html"
        },
        {
            "id": 401840867,
            "streamUrl": "https:\/\/watchasports.90live.in\/2026\/02\/santos-vs-velo-clube.html"
        },
        {
            "id": 748382,
            "streamUrl": "https:\/\/watchasports.90live.in\/2026\/02\/rayo-vallecano-vs-atletico-madrid.html"
        }
    ]
}